{"name":"kmal808 Registry","workspacecount":5,"icon":"/img/logo.svg","description":"Curated registry of custom KASM workspaces","list_url":"https://kmal808.github.io/kasm-registry/","contact_url":"https://github.com/kmal808/kasm-registry/issues","modified":1706012805767,"workspaces":[{"friendly_name":"Apache Guacamole","image_src":"blob:https://jacobgaming27.github.io/f44119e9-acaf-4a52-9179-dd1e0010d865","description":"Guacamole is a new simple way to allow VNC, RDP and SSH connections easily through your web browser.","name":"dockerscripts/guacamole:develop","cores":2,"memory":2768,"gpu_count":0,"cpu_allocation_method":"Inherit","docker_registry":"https://index.docker.io/v1/","categories":["Remote Access"],"require_gpu":false,"enabled":true,"image_type":"Container","run_config":{"hostname":"kasm"},"exec_config":{"go":{"cmd":"bash -c '/dockerstartup/custom_startup.sh --go --url \"$KASM_URL\"'"},"assign":{"cmd":"bash -c '/dockerstartup/custom_startup.sh --assign --url \"$KASM_URL\"'"}},"architecture":["amd64","arm64"],"compatibility":["1.13.x","1.14.x"],"uncompressed_size_mb":2170,"sha":"60eb981f7f117f201742134023d2bce052242e44"},{"description":"Chromium is a free and open-source browser, primarily developed and maintained by Google.","docker_registry":"https://index.docker.io/v1/","image_src":"chromium.png","name":"kasmweb/chromium:develop","run_config":{"hostname":"kasm"},"exec_config":{"go":{"cmd":"bash -c '/dockerstartup/custom_startup.sh --go --url \"$KASM_URL\"'"},"assign":{"cmd":"bash -c '/dockerstartup/custom_startup.sh --assign --url \"$KASM_URL\"'"}},"categories":["Browser"],"friendly_name":"Chromium","architecture":["amd64","arm64"],"compatibility":["1.13.x","1.14.x"],"uncompressed_size_mb":2170,"sha":"f15deb0431ceedc4389a2340697ede54f9379ada"},{"description":"Free online diagraming for all","docker_registry":"https://index.docker.io/v1/","image_src":"draw.png","name":"jgraph/drawio:latest","run_config":{"hostname":"kasm"},"exec_config":{"go":{"cmd":"bash -c '/dockerstartup/custom_startup.sh --go --url \"$KASM_URL\"'"},"assign":{"cmd":"bash -c '/dockerstartup/custom_startup.sh --assign --url \"$KASM_URL\"'"}},"categories":["Productivity"],"friendly_name":"Draw.io","architecture":["amd64","arm64"],"compatibility":["1.13.x","1.14.x"],"uncompressed_size_mb":2170,"sha":"e88153258ff1d0962a1dc85616be23b255b926df"},{"description":"Jupyter Notebooks Data Science Desktop Environment","docker_registry":"https://index.docker.io/v1/","image_src":"jupyter.png","name":"doctorwhen/kasm:jupyter","friendly_name":"Jupyter","cores":2,"memory":4096,"gpu_count":0,"cpu_allocation_method":"Inherit","run_config":{"hostname":"kasm-jupyter"},"exec_config":{"first_launch":{"user":"root","cmd":"bash -c 'echo \"kasm-user  ALL=(ALL) NOPASSWD: ALL\" >> /etc/sudoers'"}},"categories":["Desktop","Productivity"],"architecture":["amd64"],"compatibility":["1.14.x"],"uncompressed_size_mb":20300,"sha":"79b2ee48092f379ab9967a5d46f44f82e64a83df"},{"friendly_name":"Obsidian","image_src":"obsidian.ico","description":"Browser accessible version of Obsidian","name":"bambam018/kasmweb-obsidian:latest","cores":2,"memory":2768,"gpu_count":0,"uncompressed_size_mb":6144,"cpu_allocation_method":"Inherit","docker_registry":"https://index.docker.io/v1/","categories":["Productivity","Office"],"require_gpu":false,"enabled":true,"image_type":"Container","architecture":["amd64"],"compatibility":["1.14.x"],"sha":"27258bf7d8b407b1a3ce0cb339b95f2a2900f58a"}]}